README.md
setup.py
DataAutomation/DataAutomation.py
DataAutomation/__init__.py
DataAutomation.egg-info/PKG-INFO
DataAutomation.egg-info/SOURCES.txt
DataAutomation.egg-info/dependency_links.txt
DataAutomation.egg-info/not-zip-safe
DataAutomation.egg-info/top_level.txt