Metadata-Version: 2.1
Name: DataAutomation
Version: 0.3
Summary: Data Automation tool which helps to automate the boring process of data science task
Author: Himanshu R Singh
